cellsepi/__init__.py
cellsepi/__main__.py
cellsepi/backend/__init__.py
cellsepi/backend/drawing_window/__init__.py
cellsepi/backend/drawing_window/drawing_util.py
cellsepi/backend/main_window/__init__.py
cellsepi/backend/main_window/avg_diameter.py
cellsepi/backend/main_window/cellsepi.py
cellsepi/backend/main_window/config_file.py
cellsepi/backend/main_window/data_util.py
cellsepi/backend/main_window/expert_mode/__init__.py
cellsepi/backend/main_window/expert_mode/event_manager.py
cellsepi/backend/main_window/expert_mode/listener.py
cellsepi/backend/main_window/expert_mode/module.py
cellsepi/backend/main_window/expert_mode/modules/__init__.py
cellsepi/backend/main_window/expert_mode/modules/image_readout.py
cellsepi/backend/main_window/expert_mode/modules/image_segmentation.py
cellsepi/backend/main_window/expert_mode/modules/project_3d_to_2d.py
cellsepi/backend/main_window/expert_mode/modules/read_lif.py
cellsepi/backend/main_window/expert_mode/modules/read_tif.py
cellsepi/backend/main_window/expert_mode/modules/review.py
cellsepi/backend/main_window/expert_mode/modules/spot_detection.py
cellsepi/backend/main_window/expert_mode/pipe.py
cellsepi/backend/main_window/expert_mode/pipeline.py
cellsepi/backend/main_window/expert_mode/pipeline_storage.py
cellsepi/backend/main_window/fluorescence.py
cellsepi/backend/main_window/image_tuning.py
cellsepi/backend/main_window/images.py
cellsepi/backend/main_window/mask.py
cellsepi/backend/main_window/notifier.py
cellsepi/backend/main_window/segmentation.py
cellsepi/cli.py
cellsepi/config.json
cellsepi/csp.schema.json
cellsepi/frontend/__init__.py
cellsepi/frontend/drawing_window/__init__.py
cellsepi/frontend/drawing_window/gui_drawing.py
cellsepi/frontend/main_window/__init__.py
cellsepi/frontend/main_window/expert_mode/__init__.py
cellsepi/frontend/main_window/expert_mode/expert_constants.py
cellsepi/frontend/main_window/expert_mode/gui_builder.py
cellsepi/frontend/main_window/expert_mode/gui_expert_environment.py
cellsepi-1.1.9.9.4.dist-info/LICENSE
cellsepi-1.1.9.9.4.dist-info/METADATA
cellsepi-1.1.9.9.4.dist-info/WHEEL
cellsepi-1.1.9.9.4.dist-info/entry_points.txt
cellsepi-1.1.9.9.4.dist-info/RECORD
