Metadata-Version: 2.1
Name: cellsepi
Version: 1.1.9.9.4
Summary: Segmentation of microscopy images and data analysis pipeline with a graphical user interface, powered by Cellpose.
Home-page: https://github.com/PraiseTheDarkFlo/CellSePi
License: Apache-2.0
Author: Jenna Ahlvers
Requires-Python: >=3.8
Classifier: License :: OSI Approved :: Apache Software License
Classifier: Programming Language :: Python :: 3
Classifier: Programming Language :: Python :: 3.8
Classifier: Programming Language :: Python :: 3.9
Classifier: Programming Language :: Python :: 3.10
Classifier: Programming Language :: Python :: 3.11
Classifier: Programming Language :: Python :: 3.12
Requires-Dist: big-fish (==0.6.2)
Requires-Dist: bioio (==1.2.0)
Requires-Dist: bioio-lif
Requires-Dist: cellpose (==3.1.1.1)
Requires-Dist: flet (==0.28.3)
Requires-Dist: flet-cli (==0.28.3)
Requires-Dist: flet-desktop (==0.28.3)
Requires-Dist: flet-extended-interactive-viewer (==0.1.2)
Requires-Dist: flet-runtime (==0.24.1)
Requires-Dist: flet_contrib
Requires-Dist: flet_core (==0.24.1)
Requires-Dist: imageio (==2.11.0)
Requires-Dist: jsonschema (==4.25.1)
Requires-Dist: matplotlib
Requires-Dist: numba (==0.61.0)
Requires-Dist: numpy (==1.26.4)
Requires-Dist: openpyxl
Requires-Dist: pandas
Requires-Dist: pillow
Requires-Dist: pyqt5
Requires-Dist: torchvision (==0.17.2)
